pycx4/__init__.py
pycx4/aux.py
pycx4/pycda.cpython-36m-x86_64-linux-gnu.so
pycx4/q5cda.cpython-36m-x86_64-linux-gnu.so
pycx4/qcda.py
pycx4/version.py
pycx4-2.0.3.dist-info/METADATA
pycx4-2.0.3.dist-info/WHEEL
pycx4-2.0.3.dist-info/top_level.txt
pycx4-2.0.3.dist-info/RECORD
