Metadata-Version: 2.1
Name: pycx4
Version: 2.0.3
Summary: CXv4 control system framework Python bindings
Home-page: https://github.com/femanov/pycx4/wiki
Author: Fedor Emanov
Author-email: femanov@gmail.com
License: GPL
Download-URL: https://github.com/femanov/pycx4
Platform: Linux
Classifier: License :: OSI Approved :: GNU General Public License (GPL)
Classifier: Operating System :: POSIX
Classifier: Operating System :: POSIX :: BSD
Classifier: Operating System :: POSIX :: Linux
Classifier: Programming Language :: Python
Classifier: Programming Language :: Python :: 3
Classifier: Programming Language :: Python :: Implementation :: CPython
Classifier: Programming Language :: Cython
Classifier: Topic :: Scientific/Engineering
Classifier: Topic :: Software Development
